apns2/__init__.py
apns2/client.py
apns2/credentials.py
apns2/errors.py
apns2/payload.py
apns2_up-0.7.4.dist-info/LICENSE
apns2_up-0.7.4.dist-info/METADATA
apns2_up-0.7.4.dist-info/WHEEL
apns2_up-0.7.4.dist-info/top_level.txt
apns2_up-0.7.4.dist-info/RECORD
